Workbook

Sheet INSTRUCTIONS
B2: 📦 INVENTORY MANAGEMENT SYSTEM v1.0
B3: End-to-End Inventory Tracking, FIFO Costing & Month-End Reconciliation
B5: COLOUR CODING GUIDE
B6: Blue text on gold background | C6: Hardcoded INPUT cell — enter your data here
B7: Black text, white background | C7: FORMULA cell — calculated automatically, do not edit
B8: Green text, white background | C8: Cross-sheet LINK — pulls data from another sheet
B9: Dark navy header row | C9: Section title / sheet header
B10: Medium blue header row | C10: Column header row
B11: Light blue alternating row | C11: Data rows (alternating shading for readability)
B13: WORKBOOK SHEETS — WHAT EACH SHEET DOES
B14: Sheet Name | C14: Who Uses It | D14: Purpose
B15: Supplier_Master | C15: Finance / Admin | D15: One row per supplier. Enter supplier details, payment terms, banking info. Used as a lookup by the PO Register.
B16: Item_Master | C16: Finance / Admin | D16: One row per SKU. Tracks product details and reorder points. Current stock qty, WACC and value auto-populate from FIFO Engine.
B17: PO_Register | C17: Operations + Finance | D17: Raise and track all Purchase Orders. Operations updates receipt date & qty received. Finance updates payment milestone dates and status.
B18: Inventory_Ledger | C18: Operations + Finance | D18: Every inventory movement is logged here (PO Receipts, Sales, Shrinkage, Adjustments). This feeds all calculations downstream.
B19: FIFO_Engine | C19: Finance (read-only) | D19: Auto-calculates FIFO cost layers. One row per goods receipt batch. Shows exactly how much of each layer remains and the COGS value consumed. DO NOT edit formula columns.
B20: WACC_Summary | C20: Finance (read-only) | D20: Summarises current on-hand qty, total inventory value, and Weighted Average Cost per SKU. Feeds back into Item_Master.
B21: Monthly_Recon | C21: Finance | D21: Select the accounting period. System calculates opening inventory, purchases, COGS, shrinkage, closing inventory, and generates journal entries to post.
B23: PROCESS FLOW
B24: Step | C24: Action
B25: Step 1 — Raise PO | C25: Finance/Ops enters PO details in PO_Register. Status = 'Draft'. Add supplier, item, qty, price, free units, freight.
B26: Step 2 — Approve PO | C26: Approver reviews and updates Status = 'Approved', enters Approved_By and Approval_Date.
B27: Step 3 — Pay Deposit | C27: Finance updates Status = 'Deposit Paid' and enters Deposit_Date.
B28: Step 4 — Full Payment & Ship | C28: Finance updates Status = 'Fully Paid – Shipped' and enters Full_Payment_Date.
B29: Step 5 — Goods Received | C29: Ops updates Received_Date, Received_Qty, and Status = 'Fully Paid – Received'.
B30: Step 6 — Log in Ledger | C30: Finance adds a PO Receipt row in Inventory_Ledger (Qty_In, Unit_Cost from Effective_Unit_Cost on PO).
B31: Step 7 — Log Sales / Shrinkage | C31: Ops/Finance adds Sale or Shrinkage rows in Inventory_Ledger (Qty_Out, Unit_Cost from FIFO_Engine oldest open layer).
B32: Step 8 — Month-End Recon | C32: Finance opens Monthly_Recon, selects the period, reviews the movements and posts the generated journal entries.
B34: IMPORTANT — FIFO ENGINE RULES
B35: • The FIFO Engine sheet MUST have rows sorted by Item_ID (A→Z) and then by Receipt_Date (oldest→newest) within each item.
B36: • When you receive goods, add a new row to FIFO_Engine directly below the last row for that item (maintaining the sort order).
B37: • Only enter data in the yellow INPUT columns (Layer_ID, Item_ID, PO_Reference, Receipt_Date, Qty_Received, Unit_Cost).
B38: • All other columns in FIFO_Engine are formula-driven — copy the formulas down from the row above when adding new layers.
B39: • Unit_Cost in FIFO_Engine = Effective_Unit_Cost from the PO_Register (Total PO Value ÷ Total Qty including free units).
B40: • For the Unit_Cost of outgoing transactions in the Inventory_Ledger, use the Unit_Cost of the oldest 'Open' or 'Partial' layer in FIFO_Engine for that item.

Sheet Supplier_Master
A1: SUPPLIER MASTER
A2: Supplier ID | B2: Supplier Name | C2: Contact Name | D2: Email | E2: Phone | F2: Payment Terms | G2: Lead Time (days) | H2: Currency | I2: Bank Name | J2: Bank Account | K2: Swift / IBAN | L2: Status | M2: Notes
A3: S001 | B3: ABC Trading Co. | C3: John Smith | D3: john@abctrading.com | E3: +1-555-0101 | F3: Net 30 | G3: 14 | H3: USD | I3: First National Bank | J3: 123-456-7890 | K3: FNBAUS33 | L3: Active | M3: Primary widget supplier
A4: S002 | B4: XYZ Manufacturing | C4: Li Wei | D4: lwei@xyzman.com | E4: +86-21-55550202 | F4: Net 60 | G4: 21 | H4: USD | I4: Bank of China | J4: 987-654-3210 | K4: BKCHCNBJ | L4: Active | M4: Main manufacturing partner
A5: S003 | B5: Fresh Goods Ltd. | C5: Emma Brown | D5: emma@freshgoods.co | E5: +44-20-75550303 | F5: Net 45 | G5: 7 | H5: GBP | I5: Barclays PLC | J5: 111-222-3333 | K5: BARCGB22 | L5: Active | M5: Fast-turnaround supplier

Sheet Item_Master
A1: ITEM MASTER
A2: Item ID | B2: Item Name | C2: Description | D2: Category | E2: Unit of Measure | F2: Reorder Point | G2: Std Lead Days | H2: Preferred Supplier | I2: Qty On Hand | J2: Current WACC ($) | K2: Inventory Value ($) | L2: Status | M2: Notes
A3: I001 | B3: Widget A | C3: Standard Widget – Type A | D3: Electronics | E3: Units | F3: 100 | G3: 14 | H3: S001 | I3: =IFERROR(VLOOKUP(A3,WACC_Summary!$A:$D,3,0),0) -> 640 | J3: =IFERROR(VLOOKUP(A3,WACC_Summary!$A:$E,5,0),0) -> 4.9524 | K3: =IFERROR(VLOOKUP(A3,WACC_Summary!$A:$D,4,0),0) -> 3169.536 | L3: Active
A4: I002 | B4: Widget B | C4: Premium Widget – Type B | D4: Electronics | E4: Units | F4: 50 | G4: 21 | H4: S002 | I4: =IFERROR(VLOOKUP(A4,WACC_Summary!$A:$D,3,0),0) -> 300 | J4: =IFERROR(VLOOKUP(A4,WACC_Summary!$A:$E,5,0),0) -> 12.3 | K4: =IFERROR(VLOOKUP(A4,WACC_Summary!$A:$D,4,0),0) -> 3690 | L4: Active
A5: I003 | B5: Gadget X | C5: Multi-function Gadget X | D5: Electronics | E5: Units | F5: 30 | G5: 7 | H5: S003 | I5: =IFERROR(VLOOKUP(A5,WACC_Summary!$A:$D,3,0),0) -> 0 | J5: =IFERROR(VLOOKUP(A5,WACC_Summary!$A:$E,5,0),0) -> 0 | K5: =IFERROR(VLOOKUP(A5,WACC_Summary!$A:$D,4,0),0) -> 0 | L5: Active
A6: I004 | B6: Gadget Y | C6: Compact Gadget Y | D6: Electronics | E6: Units | F6: 40 | G6: 14 | H6: S001 | I6: =IFERROR(VLOOKUP(A6,WACC_Summary!$A:$D,3,0),0) -> 0 | J6: =IFERROR(VLOOKUP(A6,WACC_Summary!$A:$E,5,0),0) -> 0 | K6: =IFERROR(VLOOKUP(A6,WACC_Summary!$A:$D,4,0),0) -> 0 | L6: Active
A7: I005 | B7: Component Z | C7: Base Component Z | D7: Components | E7: Units | F7: 200 | G7: 21 | H7: S002 | I7: =IFERROR(VLOOKUP(A7,WACC_Summary!$A:$D,3,0),0) -> 0 | J7: =IFERROR(VLOOKUP(A7,WACC_Summary!$A:$E,5,0),0) -> 0 | K7: =IFERROR(VLOOKUP(A7,WACC_Summary!$A:$D,4,0),0) -> 0 | L7: Active

Sheet PO_Register
A1: PURCHASE ORDER REGISTER
A2: PO Number | B2: PO Date | C2: Supplier ID | D2: Supplier Name | E2: Item ID | F2: Item Name | G2: Qty Ordered | H2: Unit Price | I2: Free Units | J2: Total Qty | K2: Subtotal ($) | L2: Freight ($) | M2: Other Costs ($) | N2: Total PO Value ($) | O2: Eff. Unit Cost ($) | P2: Currency | Q2: FX Rate | R2: Total Value (USD) | S2: Deposit % | T2: Deposit Amt ($) | U2: Status | V2: Raised By | W2: Approved By | X2: Approval Date | Y2: Deposit Date | Z2: Full Payment Date | AA2: Exp. Delivery Date | AB2: Received Date | AC2: Received Qty | AD2: Notes
A3: PO-2026-001 | B3: 46032 | C3: S001 | D3: =IFERROR(VLOOKUP(C3,Supplier_Master!$A:$B,2,0),"") -> ABC Trading Co. | E3: I001 | F3: =IFERROR(VLOOKUP(E3,Item_Master!$A:$B,2,0),"") -> Widget A | G3: 1000 | H3: 5 | I3: 50 | J3: =G3+I3 -> 1050 | K3: =G3*H3 -> 5000 | L3: 200 | M3: 0 | N3: =K3+L3+M3 -> 5200 | O3: =IFERROR(N3/J3,0) -> 4.952381 | P3: USD | Q3: 1 | R3: =N3*Q3 -> 5200 | S3: 0.3 | T3: =N3*S3 -> 1560 | U3: Fully Paid – Received | V3: Daniel | W3: Sarah M | X3: 46034 | Y3: 46035 | Z3: 46047 | AA3: 46050 | AB3: 46050 | AC3: 1050 | AD3: Received in full incl. 50 free units
A4: PO-2026-002 | B4: 46040 | C4: S002 | D4: =IFERROR(VLOOKUP(C4,Supplier_Master!$A:$B,2,0),"") -> XYZ Manufacturing | E4: I002 | F4: =IFERROR(VLOOKUP(E4,Item_Master!$A:$B,2,0),"") -> Widget B | G4: 500 | H4: 12 | I4: 0 | J4: =G4+I4 -> 500 | K4: =G4*H4 -> 6000 | L4: 150 | M4: 0 | N4: =K4+L4+M4 -> 6150 | O4: =IFERROR(N4/J4,0) -> 12.3 | P4: USD | Q4: 1 | R4: =N4*Q4 -> 6150 | S4: 0.3 | T4: =N4*S4 -> 1845 | U4: Fully Paid – Received | V4: Daniel | W4: Sarah M | X4: 46041 | Y4: 46042 | Z4: 46063 | AA4: 46068 | AB4: 46065 | AC4: 500 | AD4: Received in full
A5: PO-2026-003 | B5: 46073 | C5: S001 | D5: =IFERROR(VLOOKUP(C5,Supplier_Master!$A:$B,2,0),"") -> ABC Trading Co. | E5: I001 | F5: =IFERROR(VLOOKUP(E5,Item_Master!$A:$B,2,0),"") -> Widget A | G5: 800 | H5: 5.2 | I5: 0 | J5: =G5+I5 -> 800 | K5: =G5*H5 -> 4160 | L5: 180 | M5: 0 | N5: =K5+L5+M5 -> 4340 | O5: =IFERROR(N5/J5,0) -> 5.425 | P5: USD | Q5: 1 | R5: =N5*Q5 -> 4340 | S5: 0.3 | T5: =N5*S5 -> 1302 | U5: Deposit Paid | V5: Michael | W5: Sarah M | X5: 46074 | Y5: 46075 | AA5: 46096 | AD5: Awaiting shipment
A6: PO-2026-004 | B6: 46086 | C6: S003 | D6: =IFERROR(VLOOKUP(C6,Supplier_Master!$A:$B,2,0),"") -> Fresh Goods Ltd. | E6: I003 | F6: =IFERROR(VLOOKUP(E6,Item_Master!$A:$B,2,0),"") -> Gadget X | G6: 300 | H6: 8.5 | I6: 30 | J6: =G6+I6 -> 330 | K6: =G6*H6 -> 2550 | L6: 90 | M6: 0 | N6: =K6+L6+M6 -> 2640 | O6: =IFERROR(N6/J6,0) -> 8 | P6: GBP | Q6: 1.27 | R6: =N6*Q6 -> 3352.8 | S6: 0.3 | T6: =N6*S6 -> 792 | U6: Approved | V6: Michael | W6: Sarah M | X6: 46087 | AA6: 46101 | AD6: Free units: 10% bonus

Sheet Inventory_Ledger
A1: INVENTORY LEDGER — All Movements (Receipts | Sales | Shrinkage | Adjustments)
A2: Txn ID | B2: Date | C2: Period | D2: Transaction Type | E2: Reference | F2: Item ID | G2: Item Name | H2: Qty In | I2: Qty Out | J2: Unit Cost ($) | K2: Value In ($) | L2: Value Out ($) | M2: Posted By | N2: Notes
A3: TXN-001 | B3: 46050 | C3: =IFERROR(TEXT(B3,"MMM-YYYY"),"") -> Jan-2026 | D3: PO Receipt | E3: PO-2026-001 | F3: I001 | G3: =IFERROR(VLOOKUP(F3,Item_Master!$A:$B,2,0),"") -> Widget A | H3: 1050 | J3: 4.9524 | K3: =IFERROR(H3*J3,0) -> 5200.02 | L3: =IFERROR(I3*J3,0) -> 0 | M3: Daniel | N3: PO-2026-001 received in full (1,000 ordered + 50 free)
A4: TXN-002 | B4: 46065 | C4: =IFERROR(TEXT(B4,"MMM-YYYY"),"") -> Feb-2026 | D4: PO Receipt | E4: PO-2026-002 | F4: I002 | G4: =IFERROR(VLOOKUP(F4,Item_Master!$A:$B,2,0),"") -> Widget B | H4: 500 | J4: 12.3 | K4: =IFERROR(H4*J4,0) -> 6150 | L4: =IFERROR(I4*J4,0) -> 0 | M4: Daniel | N4: PO-2026-002 received in full
A5: TXN-003 | B5: 46068 | C5: =IFERROR(TEXT(B5,"MMM-YYYY"),"") -> Feb-2026 | D5: Sale | E5: INV-2026-001 | F5: I001 | G5: =IFERROR(VLOOKUP(F5,Item_Master!$A:$B,2,0),"") -> Widget A | I5: 400 | J5: 4.9524 | K5: =IFERROR(H5*J5,0) -> 0 | L5: =IFERROR(I5*J5,0) -> 1980.96 | M5: Michael | N5: Customer Order #001 — 400 units Widget A
A6: TXN-004 | B6: 46073 | C6: =IFERROR(TEXT(B6,"MMM-YYYY"),"") -> Feb-2026 | D6: Sale | E6: INV-2026-002 | F6: I002 | G6: =IFERROR(VLOOKUP(F6,Item_Master!$A:$B,2,0),"") -> Widget B | I6: 200 | J6: 12.3 | K6: =IFERROR(H6*J6,0) -> 0 | L6: =IFERROR(I6*J6,0) -> 2460 | M6: Michael | N6: Customer Order #002 — 200 units Widget B
A7: TXN-005 | B7: 46081 | C7: =IFERROR(TEXT(B7,"MMM-YYYY"),"") -> Feb-2026 | D7: Shrinkage | E7: ADJ-2026-001 | F7: I001 | G7: =IFERROR(VLOOKUP(F7,Item_Master!$A:$B,2,0),"") -> Widget A | I7: 10 | J7: 4.9524 | K7: =IFERROR(H7*J7,0) -> 0 | L7: =IFERROR(I7*J7,0) -> 49.524 | M7: Daniel | N7: Feb month-end stock count variance — 10 units
A8: TOTALS | H8: =SUM(H3:H7) -> 1550 | I8: =SUM(I3:I7) -> 610 | K8: =SUM(K3:K7) -> 11350.02 | L8: =SUM(L3:L7) -> 4490.484

Sheet FIFO_Engine
A1: FIFO ENGINE — Cost Layer Tracking | IMPORTANT: Keep sorted by Item ID then Receipt Date (oldest first)
A2: Layer ID | B2: Item ID | C2: Item Name | D2: PO Reference | E2: Receipt Date | F2: Qty Received | G2: Unit Cost ($) | H2: Cum. Qty Received | I2: Total Qty Consumed | J2: Qty Consumed (Layer) | K2: Qty Remaining | L2: Value Remaining ($) | M2: COGS Value ($) | N2: Layer Status
A3: L-001 | B3: I001 | C3: =IFERROR(VLOOKUP(B3,Item_Master!$A:$B,2,0),"") -> Widget A | D3: PO-2026-001 | E3: 46050 | F3: 1050 | G3: 4.9524 | H3: =SUMPRODUCT(($B$3:B3=B3)*($F$3:F3)) -> 1050 | I3: =SUMPRODUCT((Inventory_Ledger!$F$3:$F$500=B3)*Inventory_Ledger!$I$3:$I$500) -> 410 | J3: =MAX(0,MIN(F3,I3-(H3-F3))) -> 410 | K3: =F3-J3 -> 640 | L3: =K3*G3 -> 3169.536 | M3: =J3*G3 -> 2030.484 | N3: =IF(K3=0,"Closed",IF(K3=F3,"Open","Partial")) -> Partial
A4: L-002 | B4: I002 | C4: =IFERROR(VLOOKUP(B4,Item_Master!$A:$B,2,0),"") -> Widget B | D4: PO-2026-002 | E4: 46065 | F4: 500 | G4: 12.3 | H4: =SUMPRODUCT(($B$3:B4=B4)*($F$3:F4)) -> 500 | I4: =SUMPRODUCT((Inventory_Ledger!$F$3:$F$500=B4)*Inventory_Ledger!$I$3:$I$500) -> 200 | J4: =MAX(0,MIN(F4,I4-(H4-F4))) -> 200 | K4: =F4-J4 -> 300 | L4: =K4*G4 -> 3690 | M4: =J4*G4 -> 2460 | N4: =IF(K4=0,"Closed",IF(K4=F4,"Open","Partial")) -> Partial
A5: TOTALS | F5: =SUM(F3:F4) -> 1550 | K5: =SUM(K3:K4) -> 940 | L5: =SUM(L3:L4) -> 6859.536 | M5: =SUM(M3:M4) -> 4490.484
A7: ⚠ INPUT columns (yellow): Layer ID, Item ID, PO Reference, Receipt Date, Qty Received, Unit Cost | FORMULA columns (dark header): do not edit — copy formulas down when adding new layers

Sheet WACC_Summary
A1: WACC SUMMARY — Current Inventory Position & Weighted Average Cost (auto-calculated from FIFO Engine)
A2: Item ID | B2: Item Name | C2: Qty On Hand | D2: Inventory Value ($) | E2: WACC per Unit ($) | F2: Total COGS to Date ($) | G2: Total Qty Purchased | H2: Total Purchase Value ($) | I2: Open Layers | J2: Reorder Alert
A3: I001 | B3: =IFERROR(VLOOKUP(A3,Item_Master!$A:$B,2,0),"") -> Widget A | C3: =SUMIF(FIFO_Engine!$B:$B,A3,FIFO_Engine!$K:$K) -> 640 | D3: =SUMIF(FIFO_Engine!$B:$B,A3,FIFO_Engine!$L:$L) -> 3169.536 | E3: =IFERROR(D3/C3,0) -> 4.9524 | F3: =SUMIF(FIFO_Engine!$B:$B,A3,FIFO_Engine!$M:$M) -> 2030.484 | G3: =SUMIF(FIFO_Engine!$B:$B,A3,FIFO_Engine!$F:$F) -> 1050 | H3: =SUMPRODUCT((FIFO_Engine!$B$3:$B$200=A3)*FIFO_Engine!$F$3:$F$200*FIFO_Engine!$G$3:$G$200) -> 5200.02 | I3: =COUNTIFS(FIFO_Engine!$B:$B,A3,FIFO_Engine!$N:$N,"Open")+COUNTIFS(FIFO_Engine!$B:$B,A3,FIFO_Engine!$N:$N,"Partial") -> 1 | J3: =IF(C3<=IFERROR(VLOOKUP(A3,Item_Master!$A:$F,6,0),9999),"⚠ REORDER","✓ OK") -> ✓ OK
A4: I002 | B4: =IFERROR(VLOOKUP(A4,Item_Master!$A:$B,2,0),"") -> Widget B | C4: =SUMIF(FIFO_Engine!$B:$B,A4,FIFO_Engine!$K:$K) -> 300 | D4: =SUMIF(FIFO_Engine!$B:$B,A4,FIFO_Engine!$L:$L) -> 3690 | E4: =IFERROR(D4/C4,0) -> 12.3 | F4: =SUMIF(FIFO_Engine!$B:$B,A4,FIFO_Engine!$M:$M) -> 2460 | G4: =SUMIF(FIFO_Engine!$B:$B,A4,FIFO_Engine!$F:$F) -> 500 | H4: =SUMPRODUCT((FIFO_Engine!$B$3:$B$200=A4)*FIFO_Engine!$F$3:$F$200*FIFO_Engine!$G$3:$G$200) -> 6150 | I4: =COUNTIFS(FIFO_Engine!$B:$B,A4,FIFO_Engine!$N:$N,"Open")+COUNTIFS(FIFO_Engine!$B:$B,A4,FIFO_Engine!$N:$N,"Partial") -> 1 | J4: =IF(C4<=IFERROR(VLOOKUP(A4,Item_Master!$A:$F,6,0),9999),"⚠ REORDER","✓ OK") -> ✓ OK
A5: I003 | B5: =IFERROR(VLOOKUP(A5,Item_Master!$A:$B,2,0),"") -> Gadget X | C5: =SUMIF(FIFO_Engine!$B:$B,A5,FIFO_Engine!$K:$K) -> 0 | D5: =SUMIF(FIFO_Engine!$B:$B,A5,FIFO_Engine!$L:$L) -> 0 | E5: =IFERROR(D5/C5,0) -> 0 | F5: =SUMIF(FIFO_Engine!$B:$B,A5,FIFO_Engine!$M:$M) -> 0 | G5: =SUMIF(FIFO_Engine!$B:$B,A5,FIFO_Engine!$F:$F) -> 0 | H5: =SUMPRODUCT((FIFO_Engine!$B$3:$B$200=A5)*FIFO_Engine!$F$3:$F$200*FIFO_Engine!$G$3:$G$200) -> 0 | I5: =COUNTIFS(FIFO_Engine!$B:$B,A5,FIFO_Engine!$N:$N,"Open")+COUNTIFS(FIFO_Engine!$B:$B,A5,FIFO_Engine!$N:$N,"Partial") -> 0 | J5: =IF(C5<=IFERROR(VLOOKUP(A5,Item_Master!$A:$F,6,0),9999),"⚠ REORDER","✓ OK") -> ⚠ REORDER
A6: I004 | B6: =IFERROR(VLOOKUP(A6,Item_Master!$A:$B,2,0),"") -> Gadget Y | C6: =SUMIF(FIFO_Engine!$B:$B,A6,FIFO_Engine!$K:$K) -> 0 | D6: =SUMIF(FIFO_Engine!$B:$B,A6,FIFO_Engine!$L:$L) -> 0 | E6: =IFERROR(D6/C6,0) -> 0 | F6: =SUMIF(FIFO_Engine!$B:$B,A6,FIFO_Engine!$M:$M) -> 0 | G6: =SUMIF(FIFO_Engine!$B:$B,A6,FIFO_Engine!$F:$F) -> 0 | H6: =SUMPRODUCT((FIFO_Engine!$B$3:$B$200=A6)*FIFO_Engine!$F$3:$F$200*FIFO_Engine!$G$3:$G$200) -> 0 | I6: =COUNTIFS(FIFO_Engine!$B:$B,A6,FIFO_Engine!$N:$N,"Open")+COUNTIFS(FIFO_Engine!$B:$B,A6,FIFO_Engine!$N:$N,"Partial") -> 0 | J6: =IF(C6<=IFERROR(VLOOKUP(A6,Item_Master!$A:$F,6,0),9999),"⚠ REORDER","✓ OK") -> ⚠ REORDER
A7: I005 | B7: =IFERROR(VLOOKUP(A7,Item_Master!$A:$B,2,0),"") -> Component Z | C7: =SUMIF(FIFO_Engine!$B:$B,A7,FIFO_Engine!$K:$K) -> 0 | D7: =SUMIF(FIFO_Engine!$B:$B,A7,FIFO_Engine!$L:$L) -> 0 | E7: =IFERROR(D7/C7,0) -> 0 | F7: =SUMIF(FIFO_Engine!$B:$B,A7,FIFO_Engine!$M:$M) -> 0 | G7: =SUMIF(FIFO_Engine!$B:$B,A7,FIFO_Engine!$F:$F) -> 0 | H7: =SUMPRODUCT((FIFO_Engine!$B$3:$B$200=A7)*FIFO_Engine!$F$3:$F$200*FIFO_Engine!$G$3:$G$200) -> 0 | I7: =COUNTIFS(FIFO_Engine!$B:$B,A7,FIFO_Engine!$N:$N,"Open")+COUNTIFS(FIFO_Engine!$B:$B,A7,FIFO_Engine!$N:$N,"Partial") -> 0 | J7: =IF(C7<=IFERROR(VLOOKUP(A7,Item_Master!$A:$F,6,0),9999),"⚠ REORDER","✓ OK") -> ⚠ REORDER
A8: GRAND TOTAL | C8: =SUM(C3:C7) -> 940 | D8: =SUM(D3:D7) -> 6859.536 | E8: =IFERROR(E7,0) -> 0 | F8: =SUM(F3:F7) -> 4490.484 | G8: =SUM(G3:G7) -> 1550 | H8: =SUM(H3:H7) -> 11350.02

Sheet Monthly_Recon
A1: MONTHLY RECONCILIATION — Inventory Movements, COGS & Journal Entries
A3: Accounting Period (1st of month): | D3: 46054
D4: ← Change this date to switch periods
A5: INVENTORY MOVEMENT RECONCILIATION
A6: Item ID | B6: Item Name | C6: Opening Qty | D6: Opening Value ($) | E6: Purchases Qty | F6: Purchases Value ($) | G6: COGS Qty | H6: COGS Value ($) | I6: Shrinkage Qty | J6: Shrinkage Value ($) | K6: Closing Qty | L6: Closing Value ($) | M6: Variance | N6: Status
A7: I001 | B7: =IFERROR(VLOOKUP(A7,Item_Master!$A:$B,2,0),"") -> Widget A | C7: =SUMPRODUCT((Inventory_Ledger!$F$3:$F$500=A7)*(Inventory_Ledger!$B$3:$B$500<$D$3)*Inventory_Ledger!$H$3:$H$500)-SUMPRODUCT((Inventory_Ledger!$F$3:$F$500=A7)*(Inventory_Ledger!$B$3:$B$500<$D$3)*Inventory_Ledger!$I$3:$I$500) -> 1050 | D7: =SUMPRODUCT((Inventory_Ledger!$F$3:$F$500=A7)*(Inventory_Ledger!$B$3:$B$500<$D$3)*Inventory_Ledger!$K$3:$K$500)-SUMPRODUCT((Inventory_Ledger!$F$3:$F$500=A7)*(Inventory_Ledger!$B$3:$B$500<$D$3)*Inventory_Ledger!$L$3:$L$500) -> 5200.02 | E7: =SUMPRODUCT((Inventory_Ledger!$F$3:$F$500=A7)*(Inventory_Ledger!$B$3:$B$500>=$D$3)*(Inventory_Ledger!$B$3:$B$500<=EOMONTH($D$3,0))*(Inventory_Ledger!$D$3:$D$500="PO Receipt")*Inventory_Ledger!$H$3:$H$500) -> 0 | F7: =SUMPRODUCT((Inventory_Ledger!$F$3:$F$500=A7)*(Inventory_Ledger!$B$3:$B$500>=$D$3)*(Inventory_Ledger!$B$3:$B$500<=EOMONTH($D$3,0))*(Inventory_Ledger!$D$3:$D$500="PO Receipt")*Inventory_Ledger!$K$3:$K$500) -> 0 | G7: =SUMPRODUCT((Inventory_Ledger!$F$3:$F$500=A7)*(Inventory_Ledger!$B$3:$B$500>=$D$3)*(Inventory_Ledger!$B$3:$B$500<=EOMONTH($D$3,0))*(Inventory_Ledger!$D$3:$D$500="Sale")*Inventory_Ledger!$I$3:$I$500) -> 400 | H7: =SUMPRODUCT((Inventory_Ledger!$F$3:$F$500=A7)*(Inventory_Ledger!$B$3:$B$500>=$D$3)*(Inventory_Ledger!$B$3:$B$500<=EOMONTH($D$3,0))*(Inventory_Ledger!$D$3:$D$500="Sale")*Inventory_Ledger!$L$3:$L$500) -> 1980.96 | I7: =SUMPRODUCT((Inventory_Ledger!$F$3:$F$500=A7)*(Inventory_Ledger!$B$3:$B$500>=$D$3)*(Inventory_Ledger!$B$3:$B$500<=EOMONTH($D$3,0))*(Inventory_Ledger!$D$3:$D$500="Shrinkage")*Inventory_Ledger!$I$3:$I$500) -> 10 | J7: =SUMPRODUCT((Inventory_Ledger!$F$3:$F$500=A7)*(Inventory_Ledger!$B$3:$B$500>=$D$3)*(Inventory_Ledger!$B$3:$B$500<=EOMONTH($D$3,0))*(Inventory_Ledger!$D$3:$D$500="Shrinkage")*Inventory_Ledger!$L$3:$L$500) -> 49.524 | K7: =C7+E7-G7-I7 -> 640 | L7: =D7+F7-H7-J7 -> 3169.536 | M7: =IFERROR(VLOOKUP(A7,WACC_Summary!$A:$D,4,0),0)-L7 -> 0 | N7: =IF(ABS(M7)<0.01,"✓ Balanced","⚠ Variance") -> ✓ Balanced
A8: I002 | B8: =IFERROR(VLOOKUP(A8,Item_Master!$A:$B,2,0),"") -> Widget B | C8: =SUMPRODUCT((Inventory_Ledger!$F$3:$F$500=A8)*(Inventory_Ledger!$B$3:$B$500<$D$3)*Inventory_Ledger!$H$3:$H$500)-SUMPRODUCT((Inventory_Ledger!$F$3:$F$500=A8)*(Inventory_Ledger!$B$3:$B$500<$D$3)*Inventory_Ledger!$I$3:$I$500) -> 0 | D8: =SUMPRODUCT((Inventory_Ledger!$F$3:$F$500=A8)*(Inventory_Ledger!$B$3:$B$500<$D$3)*Inventory_Ledger!$K$3:$K$500)-SUMPRODUCT((Inventory_Ledger!$F$3:$F$500=A8)*(Inventory_Ledger!$B$3:$B$500<$D$3)*Inventory_Ledger!$L$3:$L$500) -> 0 | E8: =SUMPRODUCT((Inventory_Ledger!$F$3:$F$500=A8)*(Inventory_Ledger!$B$3:$B$500>=$D$3)*(Inventory_Ledger!$B$3:$B$500<=EOMONTH($D$3,0))*(Inventory_Ledger!$D$3:$D$500="PO Receipt")*Inventory_Ledger!$H$3:$H$500) -> 500 | F8: =SUMPRODUCT((Inventory_Ledger!$F$3:$F$500=A8)*(Inventory_Ledger!$B$3:$B$500>=$D$3)*(Inventory_Ledger!$B$3:$B$500<=EOMONTH($D$3,0))*(Inventory_Ledger!$D$3:$D$500="PO Receipt")*Inventory_Ledger!$K$3:$K$500) -> 6150 | G8: =SUMPRODUCT((Inventory_Ledger!$F$3:$F$500=A8)*(Inventory_Ledger!$B$3:$B$500>=$D$3)*(Inventory_Ledger!$B$3:$B$500<=EOMONTH($D$3,0))*(Inventory_Ledger!$D$3:$D$500="Sale")*Inventory_Ledger!$I$3:$I$500) -> 200 | H8: =SUMPRODUCT((Inventory_Ledger!$F$3:$F$500=A8)*(Inventory_Ledger!$B$3:$B$500>=$D$3)*(Inventory_Ledger!$B$3:$B$500<=EOMONTH($D$3,0))*(Inventory_Ledger!$D$3:$D$500="Sale")*Inventory_Ledger!$L$3:$L$500) -> 2460 | I8: =SUMPRODUCT((Inventory_Ledger!$F$3:$F$500=A8)*(Inventory_Ledger!$B$3:$B$500>=$D$3)*(Inventory_Ledger!$B$3:$B$500<=EOMONTH($D$3,0))*(Inventory_Ledger!$D$3:$D$500="Shrinkage")*Inventory_Ledger!$I$3:$I$500) -> 0 | J8: =SUMPRODUCT((Inventory_Ledger!$F$3:$F$500=A8)*(Inventory_Ledger!$B$3:$B$500>=$D$3)*(Inventory_Ledger!$B$3:$B$500<=EOMONTH($D$3,0))*(Inventory_Ledger!$D$3:$D$500="Shrinkage")*Inventory_Ledger!$L$3:$L$500) -> 0 | K8: =C8+E8-G8-I8 -> 300 | L8: =D8+F8-H8-J8 -> 3690 | M8: =IFERROR(VLOOKUP(A8,WACC_Summary!$A:$D,4,0),0)-L8 -> 0 | N8: =IF(ABS(M8)<0.01,"✓ Balanced","⚠ Variance") -> ✓ Balanced
A9: I003 | B9: =IFERROR(VLOOKUP(A9,Item_Master!$A:$B,2,0),"") -> Gadget X | C9: =SUMPRODUCT((Inventory_Ledger!$F$3:$F$500=A9)*(Inventory_Ledger!$B$3:$B$500<$D$3)*Inventory_Ledger!$H$3:$H$500)-SUMPRODUCT((Inventory_Ledger!$F$3:$F$500=A9)*(Inventory_Ledger!$B$3:$B$500<$D$3)*Inventory_Ledger!$I$3:$I$500) -> 0 | D9: =SUMPRODUCT((Inventory_Ledger!$F$3:$F$500=A9)*(Inventory_Ledger!$B$3:$B$500<$D$3)*Inventory_Ledger!$K$3:$K$500)-SUMPRODUCT((Inventory_Ledger!$F$3:$F$500=A9)*(Inventory_Ledger!$B$3:$B$500<$D$3)*Inventory_Ledger!$L$3:$L$500) -> 0 | E9: =SUMPRODUCT((Inventory_Ledger!$F$3:$F$500=A9)*(Inventory_Ledger!$B$3:$B$500>=$D$3)*(Inventory_Ledger!$B$3:$B$500<=EOMONTH($D$3,0))*(Inventory_Ledger!$D$3:$D$500="PO Receipt")*Inventory_Ledger!$H$3:$H$500) -> 0 | F9: =SUMPRODUCT((Inventory_Ledger!$F$3:$F$500=A9)*(Inventory_Ledger!$B$3:$B$500>=$D$3)*(Inventory_Ledger!$B$3:$B$500<=EOMONTH($D$3,0))*(Inventory_Ledger!$D$3:$D$500="PO Receipt")*Inventory_Ledger!$K$3:$K$500) -> 0 | G9: =SUMPRODUCT((Inventory_Ledger!$F$3:$F$500=A9)*(Inventory_Ledger!$B$3:$B$500>=$D$3)*(Inventory_Ledger!$B$3:$B$500<=EOMONTH($D$3,0))*(Inventory_Ledger!$D$3:$D$500="Sale")*Inventory_Ledger!$I$3:$I$500) -> 0 | H9: =SUMPRODUCT((Inventory_Ledger!$F$3:$F$500=A9)*(Inventory_Ledger!$B$3:$B$500>=$D$3)*(Inventory_Ledger!$B$3:$B$500<=EOMONTH($D$3,0))*(Inventory_Ledger!$D$3:$D$500="Sale")*Inventory_Ledger!$L$3:$L$500) -> 0 | I9: =SUMPRODUCT((Inventory_Ledger!$F$3:$F$500=A9)*(Inventory_Ledger!$B$3:$B$500>=$D$3)*(Inventory_Ledger!$B$3:$B$500<=EOMONTH($D$3,0))*(Inventory_Ledger!$D$3:$D$500="Shrinkage")*Inventory_Ledger!$I$3:$I$500) -> 0 | J9: =SUMPRODUCT((Inventory_Ledger!$F$3:$F$500=A9)*(Inventory_Ledger!$B$3:$B$500>=$D$3)*(Inventory_Ledger!$B$3:$B$500<=EOMONTH($D$3,0))*(Inventory_Ledger!$D$3:$D$500="Shrinkage")*Inventory_Ledger!$L$3:$L$500) -> 0 | K9: =C9+E9-G9-I9 -> 0 | L9: =D9+F9-H9-J9 -> 0 | M9: =IFERROR(VLOOKUP(A9,WACC_Summary!$A:$D,4,0),0)-L9 -> 0 | N9: =IF(ABS(M9)<0.01,"✓ Balanced","⚠ Variance") -> ✓ Balanced
A10: I004 | B10: =IFERROR(VLOOKUP(A10,Item_Master!$A:$B,2,0),"") -> Gadget Y | C10: =SUMPRODUCT((Inventory_Ledger!$F$3:$F$500=A10)*(Inventory_Ledger!$B$3:$B$500<$D$3)*Inventory_Ledger!$H$3:$H$500)-SUMPRODUCT((Inventory_Ledger!$F$3:$F$500=A10)*(Inventory_Ledger!$B$3:$B$500<$D$3)*Inventory_Ledger!$I$3:$I$500) -> 0 | D10: =SUMPRODUCT((Inventory_Ledger!$F$3:$F$500=A10)*(Inventory_Ledger!$B$3:$B$500<$D$3)*Inventory_Ledger!$K$3:$K$500)-SUMPRODUCT((Inventory_Ledger!$F$3:$F$500=A10)*(Inventory_Ledger!$B$3:$B$500<$D$3)*Inventory_Ledger!$L$3:$L$500) -> 0 | E10: =SUMPRODUCT((Inventory_Ledger!$F$3:$F$500=A10)*(Inventory_Ledger!$B$3:$B$500>=$D$3)*(Inventory_Ledger!$B$3:$B$500<=EOMONTH($D$3,0))*(Inventory_Ledger!$D$3:$D$500="PO Receipt")*Inventory_Ledger!$H$3:$H$500) -> 0 | F10: =SUMPRODUCT((Inventory_Ledger!$F$3:$F$500=A10)*(Inventory_Ledger!$B$3:$B$500>=$D$3)*(Inventory_Ledger!$B$3:$B$500<=EOMONTH($D$3,0))*(Inventory_Ledger!$D$3:$D$500="PO Receipt")*Inventory_Ledger!$K$3:$K$500) -> 0 | G10: =SUMPRODUCT((Inventory_Ledger!$F$3:$F$500=A10)*(Inventory_Ledger!$B$3:$B$500>=$D$3)*(Inventory_Ledger!$B$3:$B$500<=EOMONTH($D$3,0))*(Inventory_Ledger!$D$3:$D$500="Sale")*Inventory_Ledger!$I$3:$I$500) -> 0 | H10: =SUMPRODUCT((Inventory_Ledger!$F$3:$F$500=A10)*(Inventory_Ledger!$B$3:$B$500>=$D$3)*(Inventory_Ledger!$B$3:$B$500<=EOMONTH($D$3,0))*(Inventory_Ledger!$D$3:$D$500="Sale")*Inventory_Ledger!$L$3:$L$500) -> 0 | I10: =SUMPRODUCT((Inventory_Ledger!$F$3:$F$500=A10)*(Inventory_Ledger!$B$3:$B$500>=$D$3)*(Inventory_Ledger!$B$3:$B$500<=EOMONTH($D$3,0))*(Inventory_Ledger!$D$3:$D$500="Shrinkage")*Inventory_Ledger!$I$3:$I$500) -> 0 | J10: =SUMPRODUCT((Inventory_Ledger!$F$3:$F$500=A10)*(Inventory_Ledger!$B$3:$B$500>=$D$3)*(Inventory_Ledger!$B$3:$B$500<=EOMONTH($D$3,0))*(Inventory_Ledger!$D$3:$D$500="Shrinkage")*Inventory_Ledger!$L$3:$L$500) -> 0 | K10: =C10+E10-G10-I10 -> 0 | L10: =D10+F10-H10-J10 -> 0 | M10: =IFERROR(VLOOKUP(A10,WACC_Summary!$A:$D,4,0),0)-L10 -> 0 | N10: =IF(ABS(M10)<0.01,"✓ Balanced","⚠ Variance") -> ✓ Balanced
A11: I005 | B11: =IFERROR(VLOOKUP(A11,Item_Master!$A:$B,2,0),"") -> Component Z | C11: =SUMPRODUCT((Inventory_Ledger!$F$3:$F$500=A11)*(Inventory_Ledger!$B$3:$B$500<$D$3)*Inventory_Ledger!$H$3:$H$500)-SUMPRODUCT((Inventory_Ledger!$F$3:$F$500=A11)*(Inventory_Ledger!$B$3:$B$500<$D$3)*Inventory_Ledger!$I$3:$I$500) -> 0 | D11: =SUMPRODUCT((Inventory_Ledger!$F$3:$F$500=A11)*(Inventory_Ledger!$B$3:$B$500<$D$3)*Inventory_Ledger!$K$3:$K$500)-SUMPRODUCT((Inventory_Ledger!$F$3:$F$500=A11)*(Inventory_Ledger!$B$3:$B$500<$D$3)*Inventory_Ledger!$L$3:$L$500) -> 0 | E11: =SUMPRODUCT((Inventory_Ledger!$F$3:$F$500=A11)*(Inventory_Ledger!$B$3:$B$500>=$D$3)*(Inventory_Ledger!$B$3:$B$500<=EOMONTH($D$3,0))*(Inventory_Ledger!$D$3:$D$500="PO Receipt")*Inventory_Ledger!$H$3:$H$500) -> 0 | F11: =SUMPRODUCT((Inventory_Ledger!$F$3:$F$500=A11)*(Inventory_Ledger!$B$3:$B$500>=$D$3)*(Inventory_Ledger!$B$3:$B$500<=EOMONTH($D$3,0))*(Inventory_Ledger!$D$3:$D$500="PO Receipt")*Inventory_Ledger!$K$3:$K$500) -> 0 | G11: =SUMPRODUCT((Inventory_Ledger!$F$3:$F$500=A11)*(Inventory_Ledger!$B$3:$B$500>=$D$3)*(Inventory_Ledger!$B$3:$B$500<=EOMONTH($D$3,0))*(Inventory_Ledger!$D$3:$D$500="Sale")*Inventory_Ledger!$I$3:$I$500) -> 0 | H11: =SUMPRODUCT((Inventory_Ledger!$F$3:$F$500=A11)*(Inventory_Ledger!$B$3:$B$500>=$D$3)*(Inventory_Ledger!$B$3:$B$500<=EOMONTH($D$3,0))*(Inventory_Ledger!$D$3:$D$500="Sale")*Inventory_Ledger!$L$3:$L$500) -> 0 | I11: =SUMPRODUCT((Inventory_Ledger!$F$3:$F$500=A11)*(Inventory_Ledger!$B$3:$B$500>=$D$3)*(Inventory_Ledger!$B$3:$B$500<=EOMONTH($D$3,0))*(Inventory_Ledger!$D$3:$D$500="Shrinkage")*Inventory_Ledger!$I$3:$I$500) -> 0 | J11: =SUMPRODUCT((Inventory_Ledger!$F$3:$F$500=A11)*(Inventory_Ledger!$B$3:$B$500>=$D$3)*(Inventory_Ledger!$B$3:$B$500<=EOMONTH($D$3,0))*(Inventory_Ledger!$D$3:$D$500="Shrinkage")*Inventory_Ledger!$L$3:$L$500) -> 0 | K11: =C11+E11-G11-I11 -> 0 | L11: =D11+F11-H11-J11 -> 0 | M11: =IFERROR(VLOOKUP(A11,WACC_Summary!$A:$D,4,0),0)-L11 -> 0 | N11: =IF(ABS(M11)<0.01,"✓ Balanced","⚠ Variance") -> ✓ Balanced
A12: TOTALS | C12: =SUM(C7:C11) -> 1050 | D12: =SUM(D7:D11) -> 5200.02 | E12: =SUM(E7:E11) -> 500 | F12: =SUM(F7:F11) -> 6150 | G12: =SUM(G7:G11) -> 600 | H12: =SUM(H7:H11) -> 4440.96 | I12: =SUM(I7:I11) -> 10 | J12: =SUM(J7:J11) -> 49.524 | ... M12: =SUM(M7:M11) -> 0
A14: =CONCATENATE("JOURNAL ENTRIES TO POST — Period: ",TEXT($D$3,"MMM YYYY")) -> JOURNAL ENTRIES TO POST — Period: Feb 2026
A15: JE # | B15: Debit Account | C15: Credit Account | D15: Description | E15: Amount ($) | F15: Reference | G15: Notes
A16: JE-01 | B16: Inventory (Balance Sheet) | C16: Accounts Payable | D16: =CONCATENATE("Inventory receipts for ",TEXT($D$3,"MMM YYYY")) -> Inventory receipts for Feb 2026 | E16: =SUMIF(Inventory_Ledger!$D$3:$D$500,"PO Receipt",Inventory_Ledger!$K$3:$K$500)-SUMPRODUCT((Inventory_Ledger!$D$3:$D$500="PO Receipt")*(Inventory_Ledger!$B$3:$B$500<$D$3)*Inventory_Ledger!$K$3:$K$500)-SUMPRODUCT((Inventory_Ledger!$D$3:$D$500="PO Receipt")*(Inventory_Ledger!$B$3:$B$500>EOMONTH($D$3,0))*Inventory_Ledger!$K$3:$K$500) -> 6150 | F16: =CONCATENATE("See PO Register — period ",TEXT($D$3,"MMM YYYY")) -> See PO Register — period Feb 2026 | G16: DR Inventory / CR AP for all goods received in period
A17: JE-02 | B17: Cost of Sales | C17: Inventory (Balance Sheet) | D17: =CONCATENATE("COGS for ",TEXT($D$3,"MMM YYYY")) -> COGS for Feb 2026 | E17: =SUM(H7:H11) -> 4440.96 | F17: =CONCATENATE("FIFO COGS — see FIFO_Engine") -> FIFO COGS — see FIFO_Engine | G17: DR COGS / CR Inventory — FIFO cost of goods sold
A18: JE-03 | B18: Shrinkage / Write-off Expense | C18: Inventory (Balance Sheet) | D18: =CONCATENATE("Inventory shrinkage for ",TEXT($D$3,"MMM YYYY")) -> Inventory shrinkage for Feb 2026 | E18: =SUM(J7:J11) -> 49.524 | F18: =CONCATENATE("See Ledger ADJ entries") -> See Ledger ADJ entries | G18: DR Shrinkage Expense / CR Inventory
A19: JE-04 | B19: — Review if non-zero → | C19: Inventory Variance Account | D19: =CONCATENATE("Inventory variance — ",TEXT($D$3,"MMM YYYY")) -> Inventory variance — Feb 2026 | E19: =SUM(M7:M11) -> 0 | F19: Investigate before posting | G19: Post only if FIFO Engine vs Ledger variance exists after reconciliation
A22: BALANCE SHEET INVENTORY VALUE AFTER ENTRIES
A23: Inventory (B/S) closing balance per FIFO Engine: | E23: =SUMIF(FIFO_Engine!$B:$B,FIFO_Engine!$B$3,FIFO_Engine!$L:$L)+SUMIF(FIFO_Engine!$B:$B,FIFO_Engine!$B$4,FIFO_Engine!$L:$L) -> 6859.536
A24: Total inventory value per Ledger (closing): | E24: =L12 -> 6859.536
